sklearo/__init__.py
sklearo/base.py
sklearo/cv.py
sklearo/utils.py
sklearo/validation.py
sklearo/encoding/__init__.py
sklearo/encoding/base.py
sklearo/encoding/target.py
sklearo/encoding/woe.py
sklearo-0.2.5.dist-info/licenses/LICENSE
sklearo-0.2.5.dist-info/WHEEL
sklearo-0.2.5.dist-info/METADATA
sklearo-0.2.5.dist-info/RECORD
