Metadata-Version: 2.4
Name: sklearo
Version: 0.2.5
Summary: A versatile Python package featuring scikit-learn like transformers for feature preprocessing, compatible with all kind of dataframes thanks to narwhals.
Keywords: feature preprocessing,scikit-learn,machine learning
Author-email: Claudio Salvatore Arcidiacono <author@email.com>
Requires-Python: >=3.9
Classifier: Programming Language :: Python :: 3
Classifier: License :: OSI Approved :: MIT License
Classifier: Operating System :: OS Independent
License-File: LICENSE
Requires-Dist: narwhals>=1.20.1
Requires-Dist: pydantic>=2.0.0,<3.0.0
Requires-Dist: scikit-learn
Project-URL: Bug Tracker, https://github.com/ClaudioSalvatoreArcidiacono/sklearo/issues
Project-URL: Documentation, https://claudiosalvatorearcidiacono.github.io/sklearo/
Project-URL: Homepage, https://github.com/ClaudioSalvatoreArcidiacono/sklearo
